MANIFEST.in
README.rst
setup.cfg
setup.py
pykhet/__init__.py
pykhet.egg-info/PKG-INFO
pykhet.egg-info/SOURCES.txt
pykhet.egg-info/dependency_links.txt
pykhet.egg-info/requires.txt
pykhet.egg-info/top_level.txt
pykhet/components/__init__.py
pykhet/components/board.py
pykhet/components/types.py
pykhet/games/__init__.py
pykhet/games/game_types.py
pykhet/solvers/__init__.py
pykhet/solvers/minmax.py
pykhet/solvers/optimal_board.py
python_extensions/kt-extension.c
python_extensions/minmax.h
python_extensions/search.h