Metadata-Version: 1.1
Name: pykhet
Version: 0.18
Summary: A general library for the board game khet
Home-page: https://github.com/TheWiseLion/pykhet
Author: John Mecham
Author-email: jon.mecham@gmail.com
License: UNKNOWN
Download-URL: https://github.com/TheWiseLion/pykhet/tarball/0.18
Keywords: khet,boardgame,khet2.0,laser-chess,ai
Platform: UNKNOWN
Classifier: Topic :: Games/Entertainment :: Board Games
Classifier: Programming Language :: Python :: 2.7
Classifier: License :: OSI Approved :: MIT License
Classifier: Programming Language :: Python :: 3
Classifier: Programming Language :: Python :: 3.3
Classifier: Programming Language :: Python :: 3.4
Classifier: Programming Language :: Python :: 3.5
